itango/__init__.py
itango/__main__.py
itango/_version.py
itango/common.py
itango/eventlogger.py
itango/install.py
itango/itango.py
itango/resource/ITangoConsole.svg
itango/resource/database.png
itango/resource/device.png
itango/resource/motor.png
itango/resource/serial.png
itango/resource/starter.png
itango-0.3.0.dist-info/licenses/LICENSE
itango-0.3.0.dist-info/METADATA
itango-0.3.0.dist-info/WHEEL
itango-0.3.0.dist-info/entry_points.txt
itango-0.3.0.dist-info/top_level.txt
itango-0.3.0.dist-info/RECORD
