Metadata-Version: 2.4
Name: itango
Version: 0.3.0
Summary: An interactive Tango client
Author: Tiago Coutinho
Maintainer: Benjamin Bertrand
License-Expression: LGPL-3.0-or-later
Project-URL: Homepage, https://www.tango-controls.org/
Project-URL: Repository, https://gitlab.com/tango-controls/itango
Project-URL: Documentation, https://itango.readthedocs.io
Keywords: pytango,ipython
Classifier: Framework :: IPython
Classifier: Intended Audience :: Developers
Classifier: Intended Audience :: Science/Research
Classifier: Programming Language :: Python :: 3
Classifier: Topic :: System :: Shells
Requires-Python: >=3.9
License-File: LICENSE
Requires-Dist: pytango>=9.3.0
Requires-Dist: ipython<10.0,>=8.5
Requires-Dist: packaging
Provides-Extra: qt
Requires-Dist: qtconsole; extra == "qt"
Provides-Extra: tests
Requires-Dist: pytest; extra == "tests"
Requires-Dist: pytest-cov; extra == "tests"
Dynamic: license-file
